teamspeak_mcp/__init__.py
teamspeak_mcp/__main__.py
teamspeak_mcp/server.py
teamspeak_mcp-1.5.2.dist-info/licenses/LICENSE
teamspeak_mcp-1.5.2.dist-info/METADATA
teamspeak_mcp-1.5.2.dist-info/WHEEL
teamspeak_mcp-1.5.2.dist-info/entry_points.txt
teamspeak_mcp-1.5.2.dist-info/top_level.txt
teamspeak_mcp-1.5.2.dist-info/RECORD
