Metadata-Version: 2.4
Name: teamspeak-mcp
Version: 1.5.2
Summary: TeamSpeak MCP Server - Control TeamSpeak from AI models
Author-email: MarlBurroW <contact@example.com>
License: MIT
Project-URL: Homepage, https://github.com/MarlBurroW/teamspeak-mcp
Project-URL: Repository, https://github.com/MarlBurroW/teamspeak-mcp
Project-URL: Issues, https://github.com/MarlBurroW/teamspeak-mcp/issues
Classifier: Development Status :: 4 - Beta
Classifier: Intended Audience :: Developers
Classifier: License :: OSI Approved :: MIT License
Classifier: Programming Language :: Python :: 3
Classifier: Programming Language :: Python :: 3.10
Classifier: Programming Language :: Python :: 3.11
Classifier: Programming Language :: Python :: 3.12
Requires-Python: <3.13,>=3.10
License-File: LICENSE
Requires-Dist: mcp>=1.9.0
Requires-Dist: ts3>=1.0.11
Requires-Dist: pydantic>=2.11.0
Dynamic: license-file
